Metadata-Version: 2.1
Name: calldict
Version: 0.13
Summary: Protocol to markup and evaluate functions in data structures
Home-page: https://github.com/kalemas/calldict
Author: Konstantin Maslyuk
Author-email: kostyamaslyuk@gmail.com
License: UNKNOWN
Download-URL: https://github.com/kalemas/calldict/archive/master.zip
Keywords: dict,evaluation,yaml
Platform: UNKNOWN
Provides-Extra: dev
Provides-Extra: test
License-File: LICENSE.txt
